AFG_Gumball/LICENSE
AFG_Gumball/README.md
AFG_Gumball/__init__.py
AFG_Gumball/medical_ai/__init__.py
AFG_Gumball/medical_ai/doctor_diagnostic_ai.py
AFG_Gumball/medical_ai/doctor_diagnostic_ai.pyi
AFG_Gumball/medical_ai/doctor_enhance_ai.py
AFG_Gumball/medical_ai/doctor_enhance_ai.pyi
AFG_Gumball/medical_ai/gemini_client.py
AFG_Gumball/medical_ai/patient_ai.py
AFG_Gumball/medical_ai/patient_ai.pyi
AFG_Gumball/medical_ai/xray_analysis_expert_ai.py
AFG_Gumball/medical_ai/xray_analysis_expert_ai.pyi
AFG_Gumball/torchxrayvision/__init__.py
AFG_Gumball/torchxrayvision/_version.py
AFG_Gumball/torchxrayvision/autoencoders.py
AFG_Gumball/torchxrayvision/datasets.py
AFG_Gumball/torchxrayvision/models.py
AFG_Gumball/torchxrayvision/utils.py
AFG_Gumball/torchxrayvision/baseline_models/__init__.py
AFG_Gumball/torchxrayvision/baseline_models/chexpert/__init__.py
AFG_Gumball/torchxrayvision/baseline_models/chexpert/model.py
AFG_Gumball/torchxrayvision/baseline_models/emory_hiti/__init__.py
AFG_Gumball/torchxrayvision/baseline_models/gumball/__init__.py
AFG_Gumball/torchxrayvision/baseline_models/gumball/config/__init__.py
AFG_Gumball/torchxrayvision/baseline_models/gumball/model/__init__.py
AFG_Gumball/torchxrayvision/baseline_models/gumball/model/attention_map.py
AFG_Gumball/torchxrayvision/baseline_models/gumball/model/classifier.py
AFG_Gumball/torchxrayvision/baseline_models/gumball/model/global_pool.py
AFG_Gumball/torchxrayvision/baseline_models/gumball/model/utils.py
AFG_Gumball/torchxrayvision/baseline_models/gumball/model/backbone/__init__.py
AFG_Gumball/torchxrayvision/baseline_models/gumball/model/backbone/densenet.py
AFG_Gumball/torchxrayvision/baseline_models/gumball/model/backbone/inception.py
AFG_Gumball/torchxrayvision/baseline_models/gumball/model/backbone/vgg.py
AFG_Gumball/torchxrayvision/baseline_models/gumball/ptsemseg/__init__.py
AFG_Gumball/torchxrayvision/baseline_models/gumball/ptsemseg/pspnet.py
afg_gumball-0.2.0.dist-info/licenses/LICENSE
afg_gumball-0.2.0.dist-info/METADATA
afg_gumball-0.2.0.dist-info/WHEEL
afg_gumball-0.2.0.dist-info/top_level.txt
afg_gumball-0.2.0.dist-info/RECORD
