Metadata-Version: 2.4
Name: AFG_Gumball
Version: 0.2.0
Summary: A Python package for processing medical X-ray images and AI-based diagnosis
Author-email: KienTF <kienpc872009@gmail.com>
License-Expression: Apache-2.0
Project-URL: Homepage, https://github.com/KienPC1234/AI-FOR-GOOD-2025-Gumball
Classifier: Programming Language :: Python :: 3
Classifier: Programming Language :: Python :: 3.8
Classifier: Programming Language :: Python :: 3.9
Classifier: Programming Language :: Python :: 3.10
Classifier: Programming Language :: Python :: 3.11
Classifier: Operating System :: OS Independent
Requires-Python: >=3.8
License-File: LICENSE
Requires-Dist: google-generativeai
Requires-Dist: google-genai
Requires-Dist: torch>=1.0.0
Requires-Dist: pydicom>=2.0.0
Requires-Dist: torchvision>=0.5.0
Requires-Dist: scikit-image>=0.16.0
Requires-Dist: tqdm>=4.0.0
Requires-Dist: numpy>=1.0.0
Requires-Dist: pandas>=1.0.0
Requires-Dist: requests>=1.0.0
Requires-Dist: pillow>=5.3.0
Requires-Dist: imageio>=2.0.0
Requires-Dist: python-dotenv>=0.10.0
Requires-Dist: matplotlib>=3.0.0
Dynamic: license-file
